shared_kernel/__init__.py
shared_kernel/agent_communication_channel/__init__.py
shared_kernel/agent_communication_channel/agent_channel.py
shared_kernel/agent_communication_channel/contexts.py
shared_kernel/agent_communication_channel/event_channel.py
shared_kernel/ai_audit_log/__init__.py
shared_kernel/ai_chat_persistence/__init__.py
shared_kernel/ai_chat_persistence/chat_persistence.py
shared_kernel/async_task_executor/__init__.py
shared_kernel/async_task_executor/async_task_executor.py
shared_kernel/auth/__init__.py
shared_kernel/auth/jwt_helper.py
shared_kernel/auth/token_handler.py
shared_kernel/auth/workbook_permission_handler.py
shared_kernel/batch_job/__init__.py
shared_kernel/batch_job/batch_job_status_tracker/container_job_status_tracker.py
shared_kernel/batch_job/job_handlers/__init__.py
shared_kernel/batch_job/job_handlers/aws_batch_job_handler.py
shared_kernel/batch_job/job_handlers/azure_apps_job_handler.py
shared_kernel/batch_job/job_handlers/job_handler_factory.py
shared_kernel/batch_job/job_handlers/job_status_mapper.py
shared_kernel/batch_job/job_storage_managers/__init__.py
shared_kernel/batch_job/job_storage_managers/azure_blob_storage_manager.py
shared_kernel/batch_job/job_storage_managers/job_storage_manager_factory.py
shared_kernel/batch_job/job_storage_managers/s3_job_storage_manager.py
shared_kernel/config/__init__.py
shared_kernel/constants/constants.py
shared_kernel/data_warehouse_handlers/__init__.py
shared_kernel/data_warehouse_handlers/factory.py
shared_kernel/data_warehouse_handlers/mssql_handler.py
shared_kernel/data_warehouse_handlers/mysql_handler.py
shared_kernel/data_warehouse_handlers/postgres_handler.py
shared_kernel/data_warehouse_handlers/redshift_handler.py
shared_kernel/data_warehouse_handlers/snowflake_handler.py
shared_kernel/data_warehouse_handlers/utils.py
shared_kernel/data_warehouse_handlers/warehouse_handlers_map.py
shared_kernel/data_warehouse_handlers/connections/mssql_warehouse_connection.py
fdc_shared_kernel-0.0.163.dist-info/METADATA
fdc_shared_kernel-0.0.163.dist-info/WHEEL
fdc_shared_kernel-0.0.163.dist-info/top_level.txt
fdc_shared_kernel-0.0.163.dist-info/RECORD
