Metadata-Version: 2.4
Name: fdc_shared_kernel
Version: 0.0.163
Summary: Shared library for microservice
Author-email: Shikhil S <shikhil.s@dbizsolution.com>, Ahammed Akdham N <ahammedakdham.n@dbizsolution.com>
Classifier: Programming Language :: Python :: 3
Classifier: License :: OSI Approved :: MIT License
Classifier: Operating System :: OS Independent
Requires-Python: >=3.7
Requires-Dist: alembic==1.13.2
Requires-Dist: asynctest==0.13.0
Requires-Dist: build==1.2.1
Requires-Dist: colorama==0.4.6
Requires-Dist: greenlet==3.0.3
Requires-Dist: iniconfig==2.0.0
Requires-Dist: Mako==1.3.5
Requires-Dist: MarkupSafe==2.1.5
Requires-Dist: nats-py==2.8.0
Requires-Dist: packaging==24.1
Requires-Dist: pluggy==1.5.0
Requires-Dist: psycopg2-binary==2.9.9
Requires-Dist: pytest==8.2.2
Requires-Dist: pytest-asyncio==0.23.8
Requires-Dist: python-dotenv==1.0.1
Requires-Dist: setuptools==71.0.0
Requires-Dist: SQLAlchemy==1.4.54
Requires-Dist: sqlalchemy-redshift==0.8.14
Requires-Dist: typing_extensions==4.12.2
Requires-Dist: boto3==1.35.4
Requires-Dist: azure-keyvault-secrets==4.8.0
Requires-Dist: twine==5.1.1
Requires-Dist: httpx==0.27.0
Requires-Dist: azure-identity==1.17.1
Requires-Dist: azure-servicebus==7.14.2
Requires-Dist: azure-mgmt-eventgrid==10.4.0
Requires-Dist: azure-mgmt-servicebus==9.0.0
Requires-Dist: azure-eventgrid==4.22.0
Requires-Dist: azure-storage-blob==12.26.0
Requires-Dist: azure-batch==14.2.0
Requires-Dist: azure-data-tables==12.7.0
Requires-Dist: azure-storage-queue==12.13.0
Requires-Dist: pyodbc==5.1.0
Requires-Dist: redshift_connector==2.1.2
Requires-Dist: pypika
Requires-Dist: snowflake-connector-python==3.16.0
